README.rst
setup.py
astor/__init__.py
astor/code_gen.py
astor/codegen.py
astor/file_util.py
astor/node_util.py
astor/op_util.py
astor/rtrip.py
astor/source_repr.py
astor/string_repr.py
astor/tree_walk.py
slwork/__init__.py
slwork/add_code.py
slwork/caluate_func.py
slwork/mode_4.py
slwork/mode_5.py
slwork/prepare_data.py
slwork/trans_exl.py
slwork.egg-info/PKG-INFO
slwork.egg-info/SOURCES.txt
slwork.egg-info/dependency_links.txt
slwork.egg-info/requires.txt
slwork.egg-info/top_level.txt
slwork.egg-info/zip-safe