Metadata-Version: 2.1
Name: slwork
Version: 0.0.2
Summary: Flexible, extensible Web CMS framework built on Tornado,compatible with Python 3.7 and above.
Home-page: https://bukun.coding.net/p/dev/d/slwork/git
Author: bukun
Author-email: bukun@osgeo.cn
License: MIT License
Keywords: slwork
Platform: any
Classifier: Development Status :: 3 - Alpha
Classifier: Intended Audience :: Developers
Classifier: Topic :: Software Development :: Libraries :: Python Modules
Classifier: License :: OSI Approved :: MIT License
Classifier: Programming Language :: Python :: 3
Classifier: Programming Language :: Python :: 3.7
Classifier: Programming Language :: Python :: 3.8
Classifier: Programming Language :: Python :: 3.9
Classifier: Programming Language :: Python :: 3.10
Classifier: Programming Language :: Python :: 3.11
